mdsdl/__init__.py
mdsdl/fully_connected/fully_connected.py
mdsdl-0.1.1.dist-info/LICENSE.md
mdsdl-0.1.1.dist-info/METADATA
mdsdl-0.1.1.dist-info/WHEEL
mdsdl-0.1.1.dist-info/RECORD
